[
  {
    "full_name": "romkatv/powerlevel10k",
    "stargazers_count": 46434,
    "open_issues_count": 75,
    "forks_count": 2188
  },
  {
    "full_name": "achyutneupane/Restaurants-Menu",
    "stargazers_count": 21,
    "open_issues_count": 0,
    "forks_count": 6
  },
  {
    "full_name": "Jabborbek/oAuth2-for-Hemis-platform",
    "stargazers_count": 3,
    "open_issues_count": 0,
    "forks_count": 1
  },
  {
    "full_name": "YC/coming-soon",
    "stargazers_count": 74,
    "open_issues_count": 0,
    "forks_count": 175
  },
  {
    "full_name": "ageron/handson-ml3",
    "stargazers_count": 7802,
    "open_issues_count": 103,
    "forks_count": 3119
  },
  {
    "full_name": "vsecoder/group-schedule-bot",
    "stargazers_count": 2,
    "open_issues_count": 2,
    "forks_count": 0
  },
  {
    "full_name": "pribalta/takagi_sugeno_kang_fuzzy_system",
    "stargazers_count": 7,
    "open_issues_count": 0,
    "forks_count": 4
  },
  {
    "full_name": "MRK-YT/MT-VideoCompress",
    "stargazers_count": 5,
    "open_issues_count": 0,
    "forks_count": 29
  },
  {
    "full_name": "perborgen/LogisticRegression",
    "stargazers_count": 315,
    "open_issues_count": 5,
    "forks_count": 269
  },
  {
    "full_name": "Jonibek0727/bot_our_brand",
    "stargazers_count": 1,
    "open_issues_count": 0,
    "forks_count": 0
  },
  {
    "full_name": "SawyerHood/draw-a-ui",
    "stargazers_count": 13285,
    "open_issues_count": 52,
    "forks_count": 1594
  },
  {
    "full_name": "selfedu-rus/machine_learning",
    "stargazers_count": 44,
    "open_issues_count": 0,
    "forks_count": 110
  },
  {
    "full_name": "sheensol/rocket_lms",
    "stargazers_count": 1,
    "open_issues_count": 0,
    "forks_count": 0
  },
  {
    "full_name": "Jonibek0727/Tabriknomabot",
    "stargazers_count": 1,
    "open_issues_count": 0,
    "forks_count": 0
  },
  {
    "full_name": "Jonibek0727/jaloliddin_online_shop",
    "stargazers_count": 1,
    "open_issues_count": 0,
    "forks_count": 0
  },
  {
    "full_name": "9autham/PlantDiseaseDetectionTelegramBot",
    "stargazers_count": 1,
    "open_issues_count": 0,
    "forks_count": 0
  },
  {
    "full_name": "prooxyyy/shopbot",
    "stargazers_count": 153,
    "open_issues_count": 6,
    "forks_count": 64
  },
  {
    "full_name": "sardoregamberdiyev/Django-school-site-and",
    "stargazers_count": 6,
    "open_issues_count": 0,
    "forks_count": 0
  },
  {
    "full_name": "SanjarbekSaminjonov/django-aiogram-template",
    "stargazers_count": 34,
    "open_issues_count": 2,
    "forks_count": 7
  },
  {
    "full_name": "Master-Bruno/Hack-Telegram",
    "stargazers_count": 228,
    "open_issues_count": 21,
    "forks_count": 51
  },
  {
    "full_name": "qewer33/qpaperOS",
    "stargazers_count": 461,
    "open_issues_count": 2,
    "forks_count": 22
  },
  {
    "full_name": "CalixtoElProgramador/MathSolar-Android",
    "stargazers_count": 1,
    "open_issues_count": 0,
    "forks_count": 0
  },
  {
    "full_name": "chxry/solaris",
    "stargazers_count": 3,
    "open_issues_count": 0,
    "forks_count": 0
  },
  {
    "full_name": "keerotic/spark-ar-quiz-filter-template",
    "stargazers_count": 8,
    "open_issues_count": 0,
    "forks_count": 1
  },
  {
    "full_name": "un0038998/LineFollowerRobot",
    "stargazers_count": 49,
    "open_issues_count": 3,
    "forks_count": 41
  },
  {
    "full_name": "azkazikna/libraryJGU",
    "stargazers_count": 29,
    "open_issues_count": 0,
    "forks_count": 2
  },
  {
    "full_name": "TutorProgramacion/pyqt-tutorial",
    "stargazers_count": 20,
    "open_issues_count": 0,
    "forks_count": 15
  },
  {
    "full_name": "PacktPublishing/Django-4-by-example",
    "stargazers_count": 813,
    "open_issues_count": 36,
    "forks_count": 461
  },
  {
    "full_name": "GyaneshSamanta/Arduino-Sunflower-Semiconductor-Miniproject",
    "stargazers_count": 3,
    "open_issues_count": 0,
    "forks_count": 7
  },
  {
    "full_name": "Yernazaz/main.py",
    "stargazers_count": 1,
    "open_issues_count": 0,
    "forks_count": 0
  }
]